<annotation>
	<folder>od_data</folder>
	<filename>egg_iddm94dw.jpg</filename>
	<path>C:\Users\dariu\OneDrive\Desktop\Git\FSL-PI\dataset\od_data\egg_iddm94dw.jpg</path>
	<source>
		<database>Unknown</database>
	</source>
	<size>
		<width>640</width>
		<height>360</height>
		<depth>3</depth>
	</size>
	<segmented>0</segmented>
	<object>
		<name>egg</name>
		<pose>Unspecified</pose>
		<truncated>0</truncated>
		<difficult>0</difficult>
		<bndbox>
			<xmin>246</xmin>
			<ymin>212</ymin>
			<xmax>410</xmax>
			<ymax>288</ymax>
		</bndbox>
	</object>
</annotation>
